README.md
setup.py
pydevmgr_vlt/__init__.py
pydevmgr_vlt.egg-info/PKG-INFO
pydevmgr_vlt.egg-info/SOURCES.txt
pydevmgr_vlt.egg-info/dependency_links.txt
pydevmgr_vlt.egg-info/entry_points.txt
pydevmgr_vlt.egg-info/requires.txt
pydevmgr_vlt.egg-info/top_level.txt
pydevmgr_vlt/base/__init__.py
pydevmgr_vlt/base/vltdevice.py
pydevmgr_vlt/base/vltinterface.py
pydevmgr_vlt/base/vltnode.py
pydevmgr_vlt/devices/__init__.py
pydevmgr_vlt/devices/_tools.py
pydevmgr_vlt/devices/vltiodev/__init__.py
pydevmgr_vlt/devices/vltiodev/cfg.py
pydevmgr_vlt/devices/vltiodev/ctrl.py
pydevmgr_vlt/devices/vltiodev/stat.py
pydevmgr_vlt/devices/vltmotor/__init__.py
pydevmgr_vlt/devices/vltmotor/cfg.py
pydevmgr_vlt/devices/vltmotor/ctrl.py
pydevmgr_vlt/devices/vltmotor/init_seq.py
pydevmgr_vlt/devices/vltmotor/positions.py
pydevmgr_vlt/devices/vltmotor/stat.py
pydevmgr_vlt_qt/__init__.py
pydevmgr_vlt_qt/io.py
pydevmgr_vlt_qt/vltdevice_cfg.py
pydevmgr_vlt_qt/vltdevice_ctrl.py
pydevmgr_vlt_qt/vltdevice_line.py
pydevmgr_vlt_qt/vltmotor_cfg.py
pydevmgr_vlt_qt/vltmotor_ctrl.py
pydevmgr_vlt_qt/vltmotor_line.py
pydevmgr_vlt_qt/vltmotor_plot.py