Metadata-Version: 2.1
Name: pydevmgr-vlt
Version: 0.4.dev3
Summary: UNKNOWN
Home-page: UNKNOWN
Author: Sylvain Guieu
Author-email: sylvain.guieu@univ-grenoble-alpes.fr
License: CeCILL Free Software License Agreement v2.1
Platform: UNKNOWN
Provides-Extra: QT
